[ {
  "Location" : "CR Park",
  "Advance - Cash" : 0.0,
  "Advance - Cheque/Bank" : 0.0,
  "Advance - Credit Card/Debit Card" : 0.0,
  "Advance - UPI" : 0.0,
  "Delivery - Cash" : 17084.0,
  "Delivery - Cheque/Bank" : 0.0,
  "Delivery - Credit Card/Debit Card" : 0.0,
  "Delivery - UPI" : 80246.0,
  "Package - Sale" : 0.0,
  "Customer Advance" : 8.0
}, {
  "Location" : "Defence Colony",
  "Advance - Cash" : 0.0,
  "Advance - Cheque/Bank" : 0.0,
  "Advance - Credit Card/Debit Card" : 0.0,
  "Advance - UPI" : 0.0,
  "Delivery - Cash" : 17713.0,
  "Delivery - Cheque/Bank" : 0.0,
  "Delivery - Credit Card/Debit Card" : 9640.0,
  "Delivery - UPI" : 6790.0,
  "Package - Sale" : 0.0,
  "Customer Advance" : 100.0
}, {
  "Location" : "Greenpark",
  "Advance - Cash" : 0.0,
  "Advance - Cheque/Bank" : 0.0,
  "Advance - Credit Card/Debit Card" : 0.0,
  "Advance - UPI" : 0.0,
  "Delivery - Cash" : 92969.0,
  "Delivery - Cheque/Bank" : 0.0,
  "Delivery - Credit Card/Debit Card" : 6705.0,
  "Delivery - UPI" : 59080.0,
  "Package - Sale" : 0.0,
  "Customer Advance" : 10.0
}, {
  "Location" : "Saket",
  "Advance - Cash" : 0.0,
  "Advance - Cheque/Bank" : 0.0,
  "Advance - Credit Card/Debit Card" : 0.0,
  "Advance - UPI" : 0.0,
  "Delivery - Cash" : 22222.0,
  "Delivery - Cheque/Bank" : 0.0,
  "Delivery - Credit Card/Debit Card" : 0.0,
  "Delivery - UPI" : 46447.0,
  "Package - Sale" : 0.0,
  "Customer Advance" : 0.0
} ]